fancy_cache/__init__.py
fancy_cache/cache_page.py
fancy_cache/constants.py
fancy_cache/memory.py
fancy_cache/middleware.py
fancy_cache/urls.py
fancy_cache/utils.py
fancy_cache/views.py
fancy_cache/management/__init__.py
fancy_cache/management/commands/__init__.py
fancy_cache/management/commands/fancy-urls.py
fancy_cache/templates/fancy-cache/home.html
fancy_tests/__init__.py
fancy_tests/tests/__init__.py
fancy_tests/tests/models.py
fancy_tests/tests/settings.py
fancy_tests/tests/test_command.py
fancy_tests/tests/test_memory.py
fancy_tests/tests/test_utils.py
fancy_tests/tests/test_views.py
fancy_tests/tests/urls.py
fancy_tests/tests/views.py
fancy_tests/tests/templates/home.html
django_fancy_cache-1.3.1.dist-info/LICENSE
django_fancy_cache-1.3.1.dist-info/METADATA
django_fancy_cache-1.3.1.dist-info/WHEEL
django_fancy_cache-1.3.1.dist-info/pbr.json
django_fancy_cache-1.3.1.dist-info/top_level.txt
django_fancy_cache-1.3.1.dist-info/RECORD
