Metadata-Version: 2.1
Name: django-fancy-cache
Version: 1.3.1
Summary: A Django 'cache_page' decorator on steroids
Home-page: https://github.com/peterbe/django-fancy-cache
Author: Peter Bengtsson
Author-email: mail@peterbe.com
License: BSD
Platform: UNKNOWN
Classifier: Development Status :: 4 - Beta
Classifier: Intended Audience :: Developers
Classifier: License :: OSI Approved :: BSD License
Classifier: Operating System :: OS Independent
Classifier: Programming Language :: Python
Classifier: Programming Language :: Python :: 3.8
Classifier: Programming Language :: Python :: 3.9
Classifier: Programming Language :: Python :: 3.10
Classifier: Programming Language :: Python :: 3.11
